metrics_cleaner/__init__.py
metrics_cleaner-0.1.0.dist-info/LICENSE
metrics_cleaner-0.1.0.dist-info/WHEEL
metrics_cleaner-0.1.0.dist-info/METADATA
metrics_cleaner-0.1.0.dist-info/RECORD
