Metadata-Version: 2.1
Name: metrics-cleaner
Version: 0.1.0
Summary: 
Author: westwardharbor0
Author-email: westwardharbor0@gmail.com
Requires-Python: >=3.9,<4.0
Classifier: Programming Language :: Python :: 3
Classifier: Programming Language :: Python :: 3.9
Requires-Dist: prometheus-client (>=0.15.0,<0.16.0)
